aletheia/__init__.cp310-win_amd64.pyd
aletheia/aletheia.cp310-win_amd64.pyd
aletheia/flatten.cp310-win_amd64.pyd
aletheia/merge.cp310-win_amd64.pyd
aletheia/prune.cp310-win_amd64.pyd
aletheia_dnn-1.3.5.dist-info/LICENSE
aletheia_dnn-1.3.5.dist-info/METADATA
aletheia_dnn-1.3.5.dist-info/WHEEL
aletheia_dnn-1.3.5.dist-info/top_level.txt
aletheia_dnn-1.3.5.dist-info/RECORD
