Metadata-Version: 2.1
Name: aletheia-dnn
Version: 1.3.5
Summary: Unwrapping ReLU Networks
Home-page: https://github.com/SelfExplainML/Aletheia
Author: Zebin Yang and Aijun Zhang and Agus Sudjianto
Author-email: yangzb2010@connect.hku.hk
License: BSD
Classifier: Development Status :: 4 - Beta
Classifier: Environment :: Console
Classifier: License :: OSI Approved :: BSD License
Classifier: Operating System :: MacOS :: MacOS X
Classifier: Operating System :: Microsoft :: Windows
Classifier: Operating System :: POSIX
Classifier: Programming Language :: Python :: 3.7
Classifier: Programming Language :: Python :: 3.8
Classifier: Programming Language :: Python :: 3.9
Classifier: Programming Language :: Python :: 3.10
License-File: LICENSE
Requires-Dist: matplotlib (>=3.1.3)
Requires-Dist: numpy (>=1.18)
Requires-Dist: pandas (>=1.1.2)
Requires-Dist: seaborn (>=0.9.0)
Requires-Dist: scikit-learn (>=0.24.2)
Requires-Dist: statsmodels (>=0.12.2)
